Workbook

Sheet README
A1: Excel Practice Dataset: Retail Sales 2025
A2: Fictional data created for practice. It is not real company data. Amounts are in South African Rand (R).
A4: Sheets
A5: Sales_Data: 600 orders (Jan–Dec 2025). Revenue is a formula = Quantity × Unit Price × (1 − Discount).
A6: Products: product list with category and cost price, for practising lookups (VLOOKUP / INDEX-MATCH).
A8: Practice tasks (do them in order)
A9: 1. Data cleaning: check for blanks and duplicates, and make sure dates and numbers have the right format.
A10: 2. Add helper columns: Month (=TEXT(date,"mmm")), Quarter, and Profit (use a lookup to Products for Cost Price).
A11: 3. Formulas: total revenue, average order value, SUMIFS revenue by region, COUNTIFS orders by category.
A12: 4. Pivot tables: revenue by month, revenue by region, top 5 products, revenue by sales rep.
A13: 5. Charts: line (monthly revenue trend), bar (revenue by region), pie/donut (category share).
A14: 6. Dashboard: new sheet with KPI cards (Total Revenue, Orders, Avg Order Value, Profit) + 3–4 charts + slicers (Region, Category).
... A17: Tip: save your finished dashboard as a portfolio project and describe it using: question → steps → findings → recommendations.

Sheet Tables Sheet
A3: Row Labels | B3: Sum of Revenue (R) | D3: Row Labels | E3: Sum of Revenue (R) | G3: Row Labels | H3: Sum of Revenue (R) | J3: Row Labels | K3: Sum of Revenue (R) | N3: Month | O3: Revenue
A4: Free State | B4: 247367.5 | D4: Accessories | E4: 155812 | G4: Apr | H4: 270559.5 | J4: Desk | K4: 301140 | N4: Jan | O4: =VLOOKUP(N4,$G$4:$H$15,2,FALSE) -> 365541.25
A5: Eastern Cape | B5: 408069.75 | D5: Electronics | E5: 2845582.5 | G5: Aug | H5: 344199 | J5: Smartwatch | K5: 344565 | N5: Feb | O5: =VLOOKUP(N5,$G$4:$H$15,2,FALSE) -> 439157
A6: Limpopo | B6: 452890 | D6: Furniture | E6: 740660 | G6: Dec | H6: 306667.25 | J6: Tablet | K6: 530820 | N6: Mar | O6: =VLOOKUP(N6,$G$4:$H$15,2,FALSE) -> 299311.75
A7: Western Cape | B7: 685785.25 | D7: Stationery | E7: 347528 | G7: Feb | H7: 439157 | J7: Smartphone | K7: 806060 | N7: Apr | O7: =VLOOKUP(N7,$G$4:$H$15,2,FALSE) -> 270559.5
A8: KwaZulu-Natal | B8: 805537 | D8: Grand Total | E8: 4089582.5 | G8: Jan | H8: 365541.25 | J8: Laptop | K8: 1041250 | N8: May | O8: =VLOOKUP(N8,$G$4:$H$15,2,FALSE) -> 283627
A9: Gauteng | B9: 1489933 | G9: Jul | H9: 341656 | J9: Grand Total | K9: 3023835 | N9: Jun | O9: =VLOOKUP(N9,$G$4:$H$15,2,FALSE) -> 283461
A10: Grand Total | B10: 4089582.5 | G10: Jun | H10: 283461 | N10: Jul | O10: =VLOOKUP(N10,$G$4:$H$15,2,FALSE) -> 341656
G11: Mar | H11: 299311.75 | N11: Aug | O11: =VLOOKUP(N11,$G$4:$H$15,2,FALSE) -> 344199
G12: May | H12: 283627 | N12: Sep | O12: =VLOOKUP(N12,$G$4:$H$15,2,FALSE) -> 415177
G13: Nov | H13: 308315.5 | N13: Oct | O13: =VLOOKUP(N13,$G$4:$H$15,2,FALSE) -> 431910.25
G14: Oct | H14: 431910.25 | N14: Nov | O14: =VLOOKUP(N14,$G$4:$H$15,2,FALSE) -> 308315.5
G15: Sep | H15: 415177 | N15: Dec | O15: =VLOOKUP(N15,$G$4:$H$15,2,FALSE) -> 306667.25
G16: Grand Total | H16: 4089582.5

Sheet Sales_Data
A1: Order ID | B1: Order Date | C1: Region | D1: City | E1: Category | F1: Product | G1: Quantity | H1: Unit Price (R) | I1: Discount | J1: Sales Rep | K1: Customer Type | L1: Payment Method | M1: Revenue (R) | N1: Month | O1: Quarter | P1: Cost Price | Q1: Profit
A2: ORD-1001 | B2: 45658 | C2: Free State | D2: Bloemfontein | E2: Electronics | F2: Smartphone | G2: 4 | H2: 8200 | I2: 0 | J2: Lerato K. | K2: Retail | L2: Cash | M2: =G2*H2*(1-I2) -> 32800 | N2: =TEXT(B2,"mmm") -> Jan | O2: =ROUNDUP(MONTH(B2)/3,0) -> 1 | P2: =VLOOKUP(F2,Products!A:C,3,FALSE) -> 5084 | Q2: =M2-(G2*P2) -> 12464
A3: ORD-1002 | B3: 45658 | C3: Western Cape | D3: Stellenbosch | E3: Stationery | F3: Notebook Pack | G3: 15 | H3: 120 | I3: 0 | J3: Naledi P. | K3: Business | L3: Cash | M3: =G3*H3*(1-I3) -> 1800 | N3: =TEXT(B3,"mmm") -> Jan | O3: =ROUNDUP(MONTH(B3)/3,0) -> 1 | P3: =VLOOKUP(F3,Products!A:C,3,FALSE) -> 74 | Q3: =M3-(G3*P3) -> 690
A4: ORD-1003 | B4: 45658 | C4: Free State | D4: Bloemfontein | E4: Accessories | F4: Backpack | G4: 4 | H4: 650 | I4: 0 | J4: Lerato K. | K4: Business | L4: EFT | M4: =G4*H4*(1-I4) -> 2600 | N4: =TEXT(B4,"mmm") -> Jan | O4: =ROUNDUP(MONTH(B4)/3,0) -> 1 | P4: =VLOOKUP(F4,Products!A:C,3,FALSE) -> 403 | Q4: =M4-(G4*P4) -> 988
A5: ORD-1004 | B5: 45659 | C5: KwaZulu-Natal | D5: Pietermaritzburg | E5: Accessories | F5: Power Bank | G5: 3 | H5: 520 | I5: 0 | J5: Naledi P. | K5: Retail | L5: Card | M5: =G5*H5*(1-I5) -> 1560 | N5: =TEXT(B5,"mmm") -> Jan | O5: =ROUNDUP(MONTH(B5)/3,0) -> 1 | P5: =VLOOKUP(F5,Products!A:C,3,FALSE) -> 322 | Q5: =M5-(G5*P5) -> 594
A6: ORD-1005 | B6: 45659 | C6: Gauteng | D6: Sandton | E6: Furniture | F6: Bookshelf | G6: 3 | H6: 1900 | I6: 0.1 | J6: Naledi P. | K6: Business | L6: Cash | M6: =G6*H6*(1-I6) -> 5130 | N6: =TEXT(B6,"mmm") -> Jan | O6: =ROUNDUP(MONTH(B6)/3,0) -> 1 | P6: =VLOOKUP(F6,Products!A:C,3,FALSE) -> 1178 | Q6: =M6-(G6*P6) -> 1596
A7: ORD-1006 | B7: 45659 | C7: KwaZulu-Natal | D7: Pietermaritzburg | E7: Electronics | F7: Smartphone | G7: 1 | H7: 8200 | I7: 0.1 | J7: Pieter V. | K7: Retail | L7: EFT | M7: =G7*H7*(1-I7) -> 7380 | N7: =TEXT(B7,"mmm") -> Jan | O7: =ROUNDUP(MONTH(B7)/3,0) -> 1 | P7: =VLOOKUP(F7,Products!A:C,3,FALSE) -> 5084 | Q7: =M7-(G7*P7) -> 2296
A8: ORD-1007 | B8: 45660 | C8: Gauteng | D8: Pretoria | E8: Stationery | F8: Printer Paper | G8: 24 | H8: 210 | I8: 0.15 | J8: Naledi P. | K8: Retail | L8: Card | M8: =G8*H8*(1-I8) -> 4284 | N8: =TEXT(B8,"mmm") -> Jan | O8: =ROUNDUP(MONTH(B8)/3,0) -> 1 | P8: =VLOOKUP(F8,Products!A:C,3,FALSE) -> 130 | Q8: =M8-(G8*P8) -> 1164
A9: ORD-1008 | B9: 45661 | C9: Gauteng | D9: Pretoria | E9: Electronics | F9: Laptop | G9: 1 | H9: 12500 | I9: 0 | J9: Lerato K. | K9: Business | L9: EFT | M9: =G9*H9*(1-I9) -> 12500 | N9: =TEXT(B9,"mmm") -> Jan | O9: =ROUNDUP(MONTH(B9)/3,0) -> 1 | P9: =VLOOKUP(F9,Products!A:C,3,FALSE) -> 7750 | Q9: =M9-(G9*P9) -> 4750
A10: ORD-1009 | B10: 45661 | C10: Western Cape | D10: Stellenbosch | E10: Furniture | F10: Desk | G10: 2 | H10: 3600 | I10: 0.05 | J10: Ayesha D. | K10: Retail | L10: Mobile Wallet | M10: =G10*H10*(1-I10) -> 6840 | N10: =TEXT(B10,"mmm") -> Jan | O10: =ROUNDUP(MONTH(B10)/3,0) -> 1 | P10: =VLOOKUP(F10,Products!A:C,3,FALSE) -> 2232 | Q10: =M10-(G10*P10) -> 2376
A11: ORD-1010 | B11: 45662 | C11: Western Cape | D11: Stellenbosch | E11: Stationery | F11: Pen Box | G11: 7 | H11: 85 | I11: 0.15 | J11: Sipho N. | K11: Retail | L11: Mobile Wallet | M11: =G11*H11*(1-I11) -> 505.75 | N11: =TEXT(B11,"mmm") -> Jan | O11: =ROUNDUP(MONTH(B11)/3,0) -> 1 | P11: =VLOOKUP(F11,Products!A:C,3,FALSE) -> 53 | Q11: =M11-(G11*P11) -> 134.75
A12: ORD-1011 | B12: 45663 | C12: Eastern Cape | D12: Gqeberha | E12: Electronics | F12: Headphones | G12: 3 | H12: 1450 | I12: 0.1 | J12: Ayesha D. | K12: Retail | L12: Mobile Wallet | M12: =G12*H12*(1-I12) -> 3915 | N12: =TEXT(B12,"mmm") -> Jan | O12: =ROUNDUP(MONTH(B12)/3,0) -> 1 | P12: =VLOOKUP(F12,Products!A:C,3,FALSE) -> 899 | Q12: =M12-(G12*P12) -> 1218
A13: ORD-1012 | B13: 45664 | C13: Gauteng | D13: Johannesburg | E13: Electronics | F13: Smartwatch | G13: 4 | H13: 3100 | I13: 0 | J13: Ayesha D. | K13: Retail | L13: Card | M13: =G13*H13*(1-I13) -> 12400 | N13: =TEXT(B13,"mmm") -> Jan | O13: =ROUNDUP(MONTH(B13)/3,0) -> 1 | P13: =VLOOKUP(F13,Products!A:C,3,FALSE) -> 1922 | Q13: =M13-(G13*P13) -> 4712
... A601: ORD-1600 | B601: 46022 | C601: Western Cape | D601: Cape Town | E601: Electronics | F601: Smartwatch | G601: 3 | H601: 3100 | I601: 0 | J601: Pieter V. | K601: Retail | L601: EFT | M601: =G601*H601*(1-I601) -> 9300 | N601: =TEXT(B601,"mmm") -> Dec | O601: =ROUNDUP(MONTH(B601)/3,0) -> 4 | P601: =VLOOKUP(F601,Products!A:C,3,FALSE) -> 1922 | Q601: =M601-(G601*P601) -> 3534

Sheet Products
A1: Product | B1: Category | C1: Cost Price (R)
A2: Laptop | B2: Electronics | C2: 7750
A3: Smartphone | B3: Electronics | C3: 5084
A4: Tablet | B4: Electronics | C4: 3348
A5: Desk | B5: Furniture | C5: 2232
A6: Smartwatch | B6: Electronics | C6: 1922
A7: Office Chair | B7: Furniture | C7: 1426
A8: Bookshelf | B8: Furniture | C8: 1178
A9: Headphones | B9: Electronics | C9: 899
A10: Backpack | B10: Accessories | C10: 403
A11: Power Bank | B11: Accessories | C11: 322
A12: Printer Paper | B12: Stationery | C12: 130
A13: Phone Case | B13: Accessories | C13: 112
... A15: Pen Box | B15: Stationery | C15: 53

Sheet Dashboard
